LICENSE
MANIFEST.in
README.md
setup.py
src/django_vcs_watch/__init__.py
src/django_vcs_watch/admin.py
src/django_vcs_watch/feeds.py
src/django_vcs_watch/forms.py
src/django_vcs_watch/models.py
src/django_vcs_watch/settings.py
src/django_vcs_watch/tests.py
src/django_vcs_watch/urls.py
src/django_vcs_watch/utils.py
src/django_vcs_watch/views.py
src/django_vcs_watch.egg-info/PKG-INFO
src/django_vcs_watch.egg-info/SOURCES.txt
src/django_vcs_watch.egg-info/dependency_links.txt
src/django_vcs_watch.egg-info/not-zip-safe
src/django_vcs_watch.egg-info/requires.txt
src/django_vcs_watch.egg-info/top_level.txt
src/django_vcs_watch/backends/__init__.py
src/django_vcs_watch/backends/svn.py
src/django_vcs_watch/jobs/__init__.py
src/django_vcs_watch/jobs/daily/__init__.py
src/django_vcs_watch/jobs/hourly/__init__.py
src/django_vcs_watch/jobs/hourly/update_feeds.py
src/django_vcs_watch/jobs/monthly/__init__.py
src/django_vcs_watch/jobs/weekly/__init__.py
src/django_vcs_watch/locale/ru/LC_MESSAGES/django.mo
src/django_vcs_watch/locale/ru/LC_MESSAGES/django.po
src/django_vcs_watch/templatetags/__init__.py
src/django_vcs_watch/templatetags/vcs_watch_tags.py