Metadata-Version: 1.0
Name: django-vcs-watch
Version: 0.2.2
Summary: RSS proxy for different VCS/DVCS.
Home-page: http://github.com/svetlyak40wt/django-vcs-watch/
Author: Alexander Artemenko
Author-email: svetlyak.40wt@gmail.com
License: New BSD License
Keywords: django apps svn
Platform: UNKNOWN
Classifier: Development Status :: 2 - Pre-Alpha
Classifier: Environment :: Plugins
Classifier: Framework :: Django
Classifier: Intended Audience :: Developers
Classifier: License :: OSI Approved :: BSD License
Classifier: Programming Language :: Python
Classifier: Topic :: Software Development :: Libraries :: Python Modules
